folding_at_home/__init__.py
folding_at_home/api.py
folding_at_home/main.py
folding_at_home-1.5.0.dist-info/LICENSE
folding_at_home-1.5.0.dist-info/METADATA
folding_at_home-1.5.0.dist-info/WHEEL
folding_at_home-1.5.0.dist-info/entry_points.txt
folding_at_home-1.5.0.dist-info/top_level.txt
folding_at_home-1.5.0.dist-info/RECORD
