Metadata-Version: 2.1
Name: folding-at-home
Version: 1.5.0
Summary: API and console tool which wraps Folding@Home Client API for Pause/Restart/Power commands
Home-page: https://github.com/nitrag/folding-at-home-api-python
Author: Ryan Gartin
Author-email: ryan@eagledevelopers.net
License: MIT
Keywords: folding folding@home foldingathome
Platform: UNKNOWN
Requires-Python: >=3.6
Requires-Dist: argparse
Requires-Dist: requests
